nebari_doctor/__init__.py
nebari_doctor/__main__.py
nebari_doctor/_version.py
nebari_doctor/agent.py
nebari_doctor/prompts.py
nebari_doctor/styling.py
nebari_doctor/version.py
nebari_doctor/tools/get_nebari_config.py
nebari_doctor/tools/get_nebari_docs.py
nebari_doctor/tools/get_pod_logs.py
nebari_doctor/tools/test_pod_logs.py
nebari_doctor/utils/clipboard.py
nebari_doctor-2025.3.1rc3.dist-info/METADATA
nebari_doctor-2025.3.1rc3.dist-info/WHEEL
nebari_doctor-2025.3.1rc3.dist-info/entry_points.txt
nebari_doctor-2025.3.1rc3.dist-info/RECORD
